InterfaceLibrary/CheckResult.py
InterfaceLibrary/HttpLibrary.py
InterfaceLibrary/__init__.py
InterfaceLibrary/version.py
robotframework_interfacelibrary-1.0.3.dev20.dist-info/top_level.txt
robotframework_interfacelibrary-1.0.3.dev20.dist-info/pbr.json
robotframework_interfacelibrary-1.0.3.dev20.dist-info/METADATA
robotframework_interfacelibrary-1.0.3.dev20.dist-info/DESCRIPTION.rst
robotframework_interfacelibrary-1.0.3.dev20.dist-info/metadata.json
robotframework_interfacelibrary-1.0.3.dev20.dist-info/WHEEL
robotframework_interfacelibrary-1.0.3.dev20.dist-info/RECORD
