Metadata-Version: 2.0
Name: robotframework-interfacelibrary
Version: 1.0.3.dev20
Summary: An interface wrapper library for RobotFramework
Home-page: https://github.com/Netease-AutoTest/robotframework-interfacelibrary
Author: Wu Qi, Wei Yating
Author-email: seven_five57@sina.com
License: Apache
Platform: UNKNOWN
Classifier: Environment :: Console
Classifier: Intended Audience :: Developers
Classifier: Operating System :: OS Independent
Classifier: Programming Language :: Python :: 2.7
Requires-Dist: robotframework
Requires-Dist: requests
Requires-Dist: httplib2
